roman_numerals/__init__.py
roman_numerals/py.typed
roman_numerals-3.0.0.dist-info/licenses/LICENCE.rst
roman_numerals-3.0.0.dist-info/WHEEL
roman_numerals-3.0.0.dist-info/METADATA
roman_numerals-3.0.0.dist-info/RECORD
