Metadata-Version: 2.4
Name: roman-numerals
Version: 3.0.0
Summary: Manipulate well-formed Roman numerals
Author: Adam Turner
Requires-Python: >=3.9
Classifier: Development Status :: 5 - Production/Stable
Classifier: Environment :: Console
Classifier: Intended Audience :: Developers
Classifier: License :: OSI Approved :: Zero-Clause BSD (0BSD)
Classifier: License :: CC0 1.0 Universal (CC0 1.0) Public Domain Dedication
Classifier: Operating System :: OS Independent
Classifier: Programming Language :: Python :: 3
Classifier: Programming Language :: Python :: 3 :: Only
Classifier: Programming Language :: Python :: 3.9
Classifier: Programming Language :: Python :: 3.10
Classifier: Programming Language :: Python :: 3.11
Classifier: Programming Language :: Python :: 3.12
Classifier: Programming Language :: Python :: 3.13
Classifier: Programming Language :: Python :: 3.14
License-File: LICENCE.rst
Requires-Dist: mypy==1.15.0 ; extra == "lint"
Requires-Dist: ruff==0.9.6 ; extra == "lint"
Requires-Dist: pyright==1.1.394 ; extra == "lint"
Requires-Dist: pytest>=8 ; extra == "test"
Project-URL: Changelog, https://github.com/AA-Turner/roman-numerals/blob/master/CHANGES.rst
Project-URL: Code, https://github.com/AA-Turner/roman-numerals/
Project-URL: Download, https://pypi.org/project/roman-numerals/
Project-URL: Issue tracker, https://github.com/AA-Turner/roman-numerals/issues
Provides-Extra: lint
Provides-Extra: test
